__init__.py
bitaware-0.1.1.dist-info/METADATA
bitaware-0.1.1.dist-info/WHEEL
bitaware-0.1.1.dist-info/entry_points.txt
bitaware-0.1.1.dist-info/licenses/LICENSE.md
bitaware.py
bitaware-0.1.1.dist-info/RECORD
