Metadata-Version: 2.1
Name: bitaware
Version: 0.1.1
Summary: Bitwise support for configuration
Author-Email: Wojciech Nowicki <wnowicki@me.com>
License: # MIT License
Project-URL: Homepage, https://github.com/wnowicki/bitaware
Project-URL: Source, https://github.com/wnowicki/bitaware
Requires-Python: >=3.10
Requires-Dist: pydantic>=2.11.4
